mxpi_train/Ui_cmd.py
mxpi_train/__init__.py
mxpi_train/__main__.py
mxpi_train/bg_rc.py
mxpi_train/classdata.py
mxpi_train/cmd.py
mxpi_train/datase.py
mxpi_train/msg.py
mxpi_train/showimg.py
mxpi_train/ui_about.py
mxpi_train/ui_cmdsssss.py
mxpi_train/ui_main.py
mxpi_train/ui_msg.py
mxpi_train/ui_showimg.py
mxpi_train/ModelNet/Classification/test.py
mxpi_train/ModelNet/Classification/train.py
mxpi_train/ModelNet/Classification/Weights/mobilenet_v2-b0353104.pth
mxpi_train/ModelNet/Classification/model/model.pth
mxpi_train/ModelNet/FastDev/eval.py
mxpi_train/ModelNet/FastDev/test.py
mxpi_train/ModelNet/FastDev/train.py
mxpi_train/ModelNet/FastDev/xml_to_txt.py
mxpi_train/ModelNet/FastDev/checkpoint/.gitkeep
mxpi_train/ModelNet/FastDev/configs/coco.names
mxpi_train/ModelNet/FastDev/configs/coco.yaml
mxpi_train/ModelNet/FastDev/example/ncnn/.gitkeep
mxpi_train/ModelNet/FastDev/example/ncnn/3.jpg
mxpi_train/ModelNet/FastDev/example/ncnn/FastestDet.bin
mxpi_train/ModelNet/FastDev/example/ncnn/FastestDet.cpp
mxpi_train/ModelNet/FastDev/example/ncnn/FastestDet.param
mxpi_train/ModelNet/FastDev/example/ncnn/build.sh
mxpi_train/ModelNet/FastDev/example/ncnn/result.jpg
mxpi_train/ModelNet/FastDev/example/onnx-runtime/runtime.py
mxpi_train/ModelNet/FastDev/module/custom_layers.py
mxpi_train/ModelNet/FastDev/module/detector.py
mxpi_train/ModelNet/FastDev/module/loss.py
mxpi_train/ModelNet/FastDev/module/shufflenetv2.pth
mxpi_train/ModelNet/FastDev/module/shufflenetv2.py
mxpi_train/ModelNet/FastDev/module/__pycache__/custom_layers.cpython-310.pyc
mxpi_train/ModelNet/FastDev/module/__pycache__/custom_layers.cpython-39.pyc
mxpi_train/ModelNet/FastDev/module/__pycache__/detector.cpython-310.pyc
mxpi_train/ModelNet/FastDev/module/__pycache__/detector.cpython-39.pyc
mxpi_train/ModelNet/FastDev/module/__pycache__/loss.cpython-310.pyc
mxpi_train/ModelNet/FastDev/module/__pycache__/loss.cpython-39.pyc
mxpi_train/ModelNet/FastDev/module/__pycache__/shufflenetv2.cpython-310.pyc
mxpi_train-0.5.dist-info/METADATA
mxpi_train-0.5.dist-info/WHEEL
mxpi_train-0.5.dist-info/entry_points.txt
mxpi_train-0.5.dist-info/top_level.txt
mxpi_train-0.5.dist-info/RECORD
