Metadata-Version: 2.1
Name: mxpi-train
Version: 0.5
Summary: Mxpi-train
Home-page: https://github.com/yuanyunqiang/
Author: YuanYunQiang
Author-email: 649756903@qq.com
License: MIT Licence
Keywords: pip,SICA
Platform: any
Requires-Dist: numpy
Requires-Dist: onnx
Requires-Dist: onnx-simplifier
Requires-Dist: onnxruntime
Requires-Dist: onnxsim
Requires-Dist: opencv-python
Requires-Dist: mxpi-pycocotools
Requires-Dist: PyYAML
Requires-Dist: torchsummary
Requires-Dist: tqdm
Requires-Dist: pyqt5
Requires-Dist: pywin32
Requires-Dist: torch
Requires-Dist: torchvision
Requires-Dist: torchaudio
Requires-Dist: future
Requires-Dist: tensorboard
Requires-Dist: labelimg2-zh
